{
  "locale": "zh-Hant",
  "language": "Traditional Chinese",
  "direction": "ltr",
  "status": "draft_requires_ai_linguistic_qa",
  "reviewRequired": true,
  "sourceLocale": "en",
  "pricingCopy": {
    "period": {
      "weekly": "每週",
      "monthly": "每月",
      "annual": "每年",
      "lifetime": "一度"
    },
    "trial": {
      "threeDayFree": "3 天免費試用",
      "thenPricePerPeriod": "然後 {price} {period}"
    },
    "savings": {
      "template": "節省 {percent}%",
      "annualDefault": "節省 65%"
    },
    "restore": "恢復購買",
    "manage": "管理訂閱",
    "cancellation": "隨時取消 App Store 訂閱。"
  }
}
