{
  "locale": "hu",
  "language": "Hungarian",
  "direction": "ltr",
  "status": "draft_requires_ai_linguistic_qa",
  "reviewRequired": true,
  "sourceLocale": "en",
  "headlines": {
    "home": "Tudd, mi történt legutóbb",
    "handoff": "Átadás másodpercek alatt",
    "timeline": "Minden gondoskodó pillanat egy helyen",
    "growth": "Apró emlékek, helyben mentve",
    "reminders": "Gyengéd bökések a hamarosan esedékes ellátáshoz",
    "family": "Tartsa szinkronban a gondozási kört",
    "paywall": "Nyissa meg a nyugodt babagondozást"
  }
}
